odoo/addons/shopfloor_mobile_base_auth_user/README.rst
odoo/addons/shopfloor_mobile_base_auth_user/__init__.py
odoo/addons/shopfloor_mobile_base_auth_user/__manifest__.py
odoo/addons/shopfloor_mobile_base_auth_user/demo/shopfloor_app_demo.xml
odoo/addons/shopfloor_mobile_base_auth_user/i18n/pt_BR.po
odoo/addons/shopfloor_mobile_base_auth_user/i18n/shopfloor_mobile_base_auth_user.pot
odoo/addons/shopfloor_mobile_base_auth_user/readme/CONTRIBUTORS.rst
odoo/addons/shopfloor_mobile_base_auth_user/readme/CREDITS.rst
odoo/addons/shopfloor_mobile_base_auth_user/readme/DESCRIPTION.rst
odoo/addons/shopfloor_mobile_base_auth_user/static/description/icon.png
odoo/addons/shopfloor_mobile_base_auth_user/static/description/index.html
odoo/addons/shopfloor_mobile_base_auth_user/static/wms/src/login.js
odoo/addons/shopfloor_mobile_base_auth_user/templates/assets.xml
odoo14_addon_shopfloor_mobile_base_auth_user-14.0.2.0.1.dist-info/METADATA
odoo14_addon_shopfloor_mobile_base_auth_user-14.0.2.0.1.dist-info/WHEEL
odoo14_addon_shopfloor_mobile_base_auth_user-14.0.2.0.1.dist-info/top_level.txt
odoo14_addon_shopfloor_mobile_base_auth_user-14.0.2.0.1.dist-info/RECORD
